petchoulauncher/.DS_Store
petchoulauncher/__main__.py
petchoulauncher/assets/.DS_Store
petchoulauncher/assets/back.png
petchoulauncher/assets/black.png
petchoulauncher/assets/mainIcon.png
petchoulauncher/assets/morpionIcon.png
petchoulauncher/assets/pythonLogo.png
petchoulauncher-0.1.7.dist-info/WHEEL
petchoulauncher-0.1.7.dist-info/METADATA
petchoulauncher-0.1.7.dist-info/RECORD
